icalreporting/__init__.py
icalreporting/_cli.py
icalreporting/icaltools.py
icalreporting/reporting.py
icalreporting-0.3.1.dist-info/LICENSE
icalreporting-0.3.1.dist-info/METADATA
icalreporting-0.3.1.dist-info/WHEEL
icalreporting-0.3.1.dist-info/entry_points.txt
icalreporting-0.3.1.dist-info/top_level.txt
icalreporting-0.3.1.dist-info/RECORD
