Metadata-Version: 2.1
Name: icalreporting
Version: 0.3.1
Summary: Reporting tools from ical files
Author-email: "J. Gressier" <jeremie.gressier@isae-supaero.fr>
License: MIT License
Project-URL: Homepage, https://github.com/jgressier/icalreporting
Classifier: Development Status :: 3 - Alpha
Classifier: License :: OSI Approved :: MIT License
Classifier: Natural Language :: English
Classifier: Operating System :: OS Independent
Classifier: Programming Language :: Python
Classifier: Programming Language :: Python :: 3.9
Classifier: Programming Language :: Python :: 3.10
Classifier: Programming Language :: Python :: 3.11
Classifier: Programming Language :: Python :: 3.12
Classifier: Programming Language :: Python :: 3.13
Classifier: Topic :: Software Development :: Libraries :: Python Modules
Requires-Python: >=3.9
License-File: LICENSE
Requires-Dist: pandas>=2.1
Requires-Dist: openpyxl>=3.1
Requires-Dist: ical>=4.5
Requires-Dist: icalendar
Provides-Extra: dev
Requires-Dist: pytest>=6.0; extra == "dev"
Requires-Dist: pytest-cov>=2.11.1; extra == "dev"
Requires-Dist: pylint>=2.6.0; extra == "dev"
